triarray/__init__.py
triarray/convert.py
triarray/index.py
triarray/io.py
triarray/math.py
triarray/matrix.py
triarray/util.py
triarray-0.2.1.dist-info/LICENSE
triarray-0.2.1.dist-info/METADATA
triarray-0.2.1.dist-info/WHEEL
triarray-0.2.1.dist-info/top_level.txt
triarray-0.2.1.dist-info/RECORD
