Metadata-Version: 2.1
Name: triarray
Version: 0.2.1
Summary: Tools for working with symmetric matrices in non-redundant format
Home-page: https://github.com/jlumpe/triarray
Author: Jared Lumpe
Author-email: mjlumpe@gmail.com
License: MIT
Project-URL: Documentation, http://triarray.readthedocs.io/en/latest/
Keywords: numpy array matrix symmetric pairwise distance similarity
Platform: UNKNOWN
Classifier: Development Status :: 4 - Beta
Classifier: Intended Audience :: Developers
Classifier: Intended Audience :: Science/Research
Classifier: License :: OSI Approved :: MIT License
Classifier: Operating System :: OS Independent
Classifier: Programming Language :: Python :: 3
Classifier: Topic :: Scientific/Engineering
Classifier: Topic :: Scientific/Engineering :: Mathematics
Requires-Python: >=3.5
License-File: LICENSE
Requires-Dist: numpy (>=1.11)
Requires-Dist: numba (>=0.30)
